pyrkm/__init__.py
pyrkm/circuit_utils.py
pyrkm/classifier.py
pyrkm/rbm.py
pyrkm/rkm.py
pyrkm/utils.py
pyrkm-0.1.0.dist-info/LICENSE
pyrkm-0.1.0.dist-info/METADATA
pyrkm-0.1.0.dist-info/WHEEL
pyrkm-0.1.0.dist-info/top_level.txt
pyrkm-0.1.0.dist-info/RECORD
