Metadata-Version: 2.1
Name: pyrkm
Version: 0.1.0
Summary: Machines learning to do machine-learning
Author-email: Simone Ciarella <simoneciarella@gmail.com>, Marcelo Guzmánn <guzmanjmarcelo@gmail.com>
License: Apache 2.0 License
Project-URL: homepage, https://github.com/Kirchhoff-Machines/pyrkm
Project-URL: issues, https://github.com/Kirchhoff-Machines/pyrkm/issues
Project-URL: documentation, https://pyrkm.readthedocs.io
Project-URL: changelog, https://github.com/Kirchhoff-Machines/pyrkm/releases
Keywords: python,machine learning,boltzmann machine,physical learning,equilibrium propagation
Classifier: Development Status :: 2 - Pre-Alpha
Classifier: Intended Audience :: Science/Research
Classifier: License :: OSI Approved :: Apache Software License
Classifier: Natural Language :: English
Classifier: Operating System :: OS Independent
Classifier: Programming Language :: Python :: 3
Classifier: Programming Language :: Python :: 3.10
Classifier: Programming Language :: Python :: 3.9
Classifier: Topic :: Scientific/Engineering
Requires-Python: >=3.9
License-File: LICENSE
Requires-Dist: matplotlib>=3.6.0
Requires-Dist: numpy
Requires-Dist: torch
Requires-Dist: torchvision
Requires-Dist: pandas
Requires-Dist: scipy
Provides-Extra: develop
Requires-Dist: bump-my-version; extra == "develop"
Requires-Dist: coverage[toml]; extra == "develop"
Requires-Dist: docformatter; extra == "develop"
Requires-Dist: mypy; extra == "develop"
Requires-Dist: pre-commit; extra == "develop"
Requires-Dist: pytest; extra == "develop"
Requires-Dist: pytest-mpl; extra == "develop"
Requires-Dist: pytest-dependency; extra == "develop"
Requires-Dist: pytest-image-diff; extra == "develop"
Provides-Extra: docs
Requires-Dist: markdown-include; extra == "docs"
Requires-Dist: mkdocs; extra == "docs"
Requires-Dist: mkdocs-jupyter; extra == "docs"
Requires-Dist: mkdocs-material; extra == "docs"
Requires-Dist: mkdocstrings[python]; extra == "docs"
Requires-Dist: pygments; extra == "docs"
Provides-Extra: publishing
Requires-Dist: twine; extra == "publishing"
Requires-Dist: wheel; extra == "publishing"
Requires-Dist: build; extra == "publishing"
Requires-Dist: tomllib; extra == "publishing"
